pyntcloud/__init__.py
pyntcloud/core_class.py
pyntcloud/filters/__init__.py
pyntcloud/filters/base.py
pyntcloud/filters/kdtree.py
pyntcloud/filters/xyz.py
pyntcloud/geometry/__init__.py
pyntcloud/geometry/areas.py
pyntcloud/geometry/coord_systems.py
pyntcloud/geometry/rotations.py
pyntcloud/geometry/models/__init__.py
pyntcloud/geometry/models/base.py
pyntcloud/geometry/models/plane.py
pyntcloud/geometry/models/sphere.py
pyntcloud/io/__init__.py
pyntcloud/io/ascii.py
pyntcloud/io/bin.py
pyntcloud/io/las.py
pyntcloud/io/npz.py
pyntcloud/io/obj.py
pyntcloud/io/off.py
pyntcloud/io/open3d.py
pyntcloud/io/pcd.py
pyntcloud/io/ply.py
pyntcloud/io/pyvista.py
pyntcloud/neighbors/__init__.py
pyntcloud/neighbors/k_neighbors.py
pyntcloud/neighbors/r_neighbors.py
pyntcloud/plot/__init__.py
pyntcloud/plot/common.py
pyntcloud/plot/matplotlib_backend.py
pyntcloud/plot/points.html
pyntcloud/plot/pythreejs_backend.py
pyntcloud/plot/pyvista_backend.py
pyntcloud/plot/threejs_backend.py
pyntcloud/plot/voxelgrid.html
pyntcloud/plot/voxelgrid.py
pyntcloud/plot/assets/Detector.js
pyntcloud/plot/assets/OrbitControls.js
pyntcloud/plot/assets/PLYLoader.js
pyntcloud/plot/assets/ball.png
pyntcloud/plot/assets/circle.png
pyntcloud/plot/assets/dat.gui.min.js
pyntcloud/plot/assets/disc.png
pyntcloud/plot/assets/jquery.min.js
pyntcloud/plot/assets/pyntcloud_logo.png
pyntcloud/plot/assets/pyntcloud_sprite.png
pyntcloud/plot/assets/python_logo.png
pyntcloud/plot/assets/stats.min.js
pyntcloud/plot/assets/three.min.js
pyntcloud/ransac/__init__.py
pyntcloud/ransac/fitters.py
pyntcloud/ransac/models.py
pyntcloud/ransac/samplers.py
pyntcloud/samplers/__init__.py
pyntcloud/samplers/base.py
pyntcloud/samplers/mesh.py
pyntcloud/samplers/points.py
pyntcloud/samplers/voxelgrid.py
pyntcloud/scalar_fields/__init__.py
pyntcloud/scalar_fields/base.py
pyntcloud/scalar_fields/eigenvalues.py
pyntcloud/scalar_fields/k_neighbors.py
pyntcloud/scalar_fields/normals.py
pyntcloud/scalar_fields/rgb.py
pyntcloud_yoda-0.3.1.post1.dist-info/LICENSE.md
pyntcloud_yoda-0.3.1.post1.dist-info/METADATA
pyntcloud_yoda-0.3.1.post1.dist-info/WHEEL
pyntcloud_yoda-0.3.1.post1.dist-info/top_level.txt
pyntcloud_yoda-0.3.1.post1.dist-info/RECORD
