Metadata-Version: 2.1
Name: pyntcloud-yoda
Version: 0.3.1.post1
Summary: Python library for working with 3D point clouds.
Home-page: https://github.com/daavoo/pyntcloud
Author: David de la Iglesia Castro
Author-email: daviddelaiglesiacastro@gmail.com
License: The MIT License
Classifier: Programming Language :: Python :: 3
Classifier: License :: OSI Approved :: MIT License
Classifier: Operating System :: OS Independent
Requires-Python: >3.7
License-File: LICENSE.md
Requires-Dist: numpy
Requires-Dist: scipy >=1.6.0
Requires-Dist: pandas
Provides-Extra: las
Requires-Dist: laspy ; extra == 'las'
Requires-Dist: lazrs ; extra == 'las'
Provides-Extra: numba
Requires-Dist: numba ; extra == 'numba'
Provides-Extra: plot
Requires-Dist: ipython ; extra == 'plot'
Requires-Dist: matplotlib ; extra == 'plot'
Requires-Dist: pyvista >=0.32.0 ; extra == 'plot'
